keras_utilities-0.1.27.dist-info/DESCRIPTION.rst
keras_utilities-0.1.27.dist-info/METADATA
keras_utilities-0.1.27.dist-info/RECORD
keras_utilities-0.1.27.dist-info/WHEEL
keras_utilities-0.1.27.dist-info/metadata.json
keras_utilities-0.1.27.dist-info/top_level.txt
kutilities/__init__.py
kutilities/callbacks.py
kutilities/layers.py
kutilities/helpers/__init__.py
kutilities/helpers/data_preparation.py
kutilities/helpers/generic.py
kutilities/helpers/ui.py
