Metadata-Version: 2.0
Name: keras-utilities
Version: 0.1.27
Summary: Utilities for Keras.
Home-page: https://github.com/cbaziotis/keras-utilities
Author: Christos Baziotis
Author-email: christos.baziotis@gmail.com
License: MIT
Platform: UNKNOWN
Requires-Dist: keras (==1.2.1)
Requires-Dist: matplotlib
Requires-Dist: numpy
Requires-Dist: scikit-learn
Requires-Dist: seaborn
